miners-0.1.4.dist-info/METADATA
miners-0.1.4.dist-info/WHEEL
miners-0.1.4.dist-info/license_files/LICENSE
miners/__init__.py
miners/miners.cpython-310-darwin.so
miners-0.1.4.dist-info/RECORD
