Metadata-Version: 2.1
Name: miners
Version: 0.1.4
Classifier: Programming Language :: Rust
Classifier: Programming Language :: Python :: Implementation :: CPython
Classifier: Programming Language :: Python :: Implementation :: PyPy
License-File: LICENSE
Summary: miners is a fast Rust library for the Maximal Information-based Nonparametric Exploration (MIC and MINE family)
Author: 0xCuteSocks
License: GPL v3.0
Requires-Python: >=3.7
